zeroshot_engine/__init__.py
zeroshot_engine/cli.py
zeroshot_engine/demo/__init__.py
zeroshot_engine/demo/demo_runner.py
zeroshot_engine/functions/__init__.py
zeroshot_engine/functions/base.py
zeroshot_engine/functions/custom.py
zeroshot_engine/functions/evaluate.py
zeroshot_engine/functions/izsc.py
zeroshot_engine/functions/ollama.py
zeroshot_engine/functions/openai.py
zeroshot_engine/functions/openrouter.py
zeroshot_engine/functions/utils.py
zeroshot_engine/functions/validate.py
zeroshot_engine/functions/visualization.py
zeroshot_engine-0.2.0.dist-info/licenses/LICENSE
zeroshot_engine-0.2.0.dist-info/METADATA
zeroshot_engine-0.2.0.dist-info/WHEEL
zeroshot_engine-0.2.0.dist-info/entry_points.txt
zeroshot_engine-0.2.0.dist-info/top_level.txt
zeroshot_engine-0.2.0.dist-info/RECORD
