Metadata-Version: 2.4
Name: zeroshot-engine
Version: 0.2.0
Summary: A zero-shot classification engine based on various LLM models
Author-email: Lucas Schwarz <luc.schwarz@posteo.de>
License: 
Project-URL: Homepage, https://github.com/TheLucasSchwarz/zeroshot-engine
Project-URL: Bug Tracker, https://github.com/TheLucasSchwarz/zeroshot-engine/issues
Keywords: zero-shot,classification,NLP,LLM
Classifier: Development Status :: 3 - Alpha
Classifier: Intended Audience :: Developers
Classifier: License :: OSI Approved :: Apache Software License
Classifier: Programming Language :: Python :: 3
Classifier: Programming Language :: Python :: 3.7
Requires-Python: >=3.7
License-File: LICENSE
Requires-Dist: pandas<3.0.0,>=2.0.0
Requires-Dist: numpy<3.0.0,>=2.0.0
Requires-Dist: tqdm>=4.60.0
Requires-Dist: semver>=3.0.0
Requires-Dist: scikit-learn<2.0.0,>=1.0.0
Requires-Dist: openai>=1.0.0
Requires-Dist: langchain-ollama<0.4.0,>=0.3.0
Dynamic: license-file
